ztfy.baseskin-0.2.0-py2.7-nspkg.pth
ztfy/baseskin/__init__.py
ztfy/baseskin/configure.zcml
ztfy/baseskin/form.py
ztfy/baseskin/layer.py
ztfy/baseskin/metas.py
ztfy/baseskin/metas.zcml
ztfy/baseskin/schema.py
ztfy/baseskin/skin.py
ztfy/baseskin/viewlet.py
ztfy/baseskin/widget.py
ztfy/baseskin/doctests/README.txt
ztfy/baseskin/interfaces/__init__.py
ztfy/baseskin/interfaces/container.py
ztfy/baseskin/interfaces/form.py
ztfy/baseskin/interfaces/metas.py
ztfy/baseskin/locales/ztfy.baseskin.pot
ztfy/baseskin/locales/en/LC_MESSAGES/ztfy.baseskin.mo
ztfy/baseskin/locales/en/LC_MESSAGES/ztfy.baseskin.po
ztfy/baseskin/locales/en/LC_MESSAGES/ztfy.baseskin.po~
ztfy/baseskin/locales/fr/LC_MESSAGES/ztfy.baseskin.mo
ztfy/baseskin/locales/fr/LC_MESSAGES/ztfy.baseskin.po
ztfy/baseskin/locales/fr/LC_MESSAGES/ztfy.baseskin.po~
ztfy/baseskin/tal/__init__.py
ztfy/baseskin/tal/api.py
ztfy/baseskin/tal/configure.zcml
ztfy/baseskin/tal/interfaces.py
ztfy/baseskin/tests/__init__.py
ztfy/baseskin/tests/test_docs.py
ztfy/baseskin/tests/test_docstrings.py
ztfy.baseskin-0.2.0.dist-info/METADATA
ztfy.baseskin-0.2.0.dist-info/WHEEL
ztfy.baseskin-0.2.0.dist-info/entry_points.txt
ztfy.baseskin-0.2.0.dist-info/namespace_packages.txt
ztfy.baseskin-0.2.0.dist-info/top_level.txt
ztfy.baseskin-0.2.0.dist-info/RECORD
