Metadata-Version: 2.1
Name: ztfy.baseskin
Version: 0.2.0
Summary: ZTFY base skin package
Home-page: http://hg.ztfy.org/ztfy.baseskin
Author: Thierry Florac
Author-email: tflorac@ulthar.net
License: zpl
Keywords: ZTFY skin
Platform: UNKNOWN
Classifier: Programming Language :: Python
Requires-Dist: setuptools
Requires-Dist: z3c.form
Requires-Dist: z3c.formui
Requires-Dist: z3c.jsonrpc
Requires-Dist: z3c.layer.pagelet
Requires-Dist: zope.component
Requires-Dist: zope.i18nmessageid
Requires-Dist: zope.interface
Requires-Dist: ztfy.base
Requires-Dist: ztfy.utils
Provides-Extra: test
Requires-Dist: zope.testing ; extra == 'test'
